README.md
setup.cfg
setup.py
palazzetti_sdk_asset_parser/__init__.py
palazzetti_sdk_asset_parser/asset_capabilities.py
palazzetti_sdk_asset_parser/asset_parser.py
palazzetti_sdk_asset_parser.egg-info/PKG-INFO
palazzetti_sdk_asset_parser.egg-info/SOURCES.txt
palazzetti_sdk_asset_parser.egg-info/dependency_links.txt
palazzetti_sdk_asset_parser.egg-info/requires.txt
palazzetti_sdk_asset_parser.egg-info/top_level.txt
palazzetti_sdk_asset_parser/data/asset_parser.json