Metadata-Version: 2.1
Name: palazzetti-sdk-asset-parser
Version: 1.0.10
Summary: IoT Device Capability Parser
Home-page: https://github.com/palazzetti/palazzetti-sdk-asset-parser-python
Author: Palazzetti Lelio Spa
Author-email: info@palazzetti.it
License: UNKNOWN
Platform: UNKNOWN
Requires-Python: >=3.6
